merge/README.md
merge/__init__.py
merge/merge.py
merge/API/core/1.0.0-alpha/.spectral.yml
merge/API/core/1.0.0-alpha/skg-if-openapi.yaml
merge/API/core/1.1.3/.spectral.yml
merge/API/core/1.1.3/skg-if-api.yaml
merge/API/core/current/skg-if-openapi.yaml
merge/API/ext/ra-skg.yaml
merge/API/ext/service.yml
merge/API/output/merged_output_skg-if-api.yaml_1.1.3_4f63e5d5be2a060a6ea3d5eeb404d278.yaml
ost_skg_if_api_tools-0.1.4.dist-info/licenses/LICENSE
ost_skg_if_api_tools-0.1.4.dist-info/METADATA
ost_skg_if_api_tools-0.1.4.dist-info/WHEEL
ost_skg_if_api_tools-0.1.4.dist-info/entry_points.txt
ost_skg_if_api_tools-0.1.4.dist-info/top_level.txt
ost_skg_if_api_tools-0.1.4.dist-info/RECORD
