Metadata-Version: 2.4
Name: ost-skg-if-api-tools
Version: 0.1.4
Summary: This project merges multiple OpenAPI specifications extensions into a single core specification for SKG IF.
Requires-Python: >=3.12
License-File: LICENSE
Requires-Dist: fastapi>=0.115.12
Requires-Dist: httpx>=0.28.1
Requires-Dist: pyyaml>=6.0.2
Requires-Dist: toml>=0.10.2
Requires-Dist: uvicorn>=0.34.2
Dynamic: license-file
